ain/__init__.py
ain/account.py
ain/ain.py
ain/constants.py
ain/errors.py
ain/net.py
ain/provider.py
ain/types.py
ain/wallet.py
ain/db/__init__.py
ain/db/push_id.py
ain/db/ref.py
ain/signer/__init__.py
ain/signer/default_signer.py
ain/utils/__init__.py
ain/utils/v3keystore.py
ain_py-1.3.0.dist-info/METADATA
ain_py-1.3.0.dist-info/WHEEL
ain_py-1.3.0.dist-info/top_level.txt
ain_py-1.3.0.dist-info/RECORD
