Metadata-Version: 2.1
Name: ain-py
Version: 1.3.0
Summary: AI Network Client Library for Python3
Home-page: https://github.com/ainblockchain/ain-py
Author: AIN Dev Team
Author-email: dev@ainetwork.ai
License: MPL license
Keywords: ain,ainetwork,ainblockchain,API
Classifier: Development Status :: 4 - Beta
Classifier: Intended Audience :: Developers
Classifier: License :: OSI Approved :: Mozilla Public License 2.0 (MPL 2.0)
Classifier: Natural Language :: English
Classifier: Programming Language :: Python :: 3
Classifier: Programming Language :: Python :: 3.7
Classifier: Programming Language :: Python :: 3.8
Classifier: Programming Language :: Python :: 3.9
Classifier: Programming Language :: Python :: 3.10
Classifier: Programming Language :: Python :: 3.11
Requires-Python: >=3.7
Requires-Dist: typing-extensions
Requires-Dist: pycryptodome ==3.18.0
Requires-Dist: coincurve ==18.0.0
Requires-Dist: aiohttp[speedups] ==3.8.5
Requires-Dist: jsonrpcclient ==4.0.3
Requires-Dist: mnemonic ==0.20
Requires-Dist: bip32 ==3.4
